splitticai/__init__.py
Splittic-5.0.dist-info/METADATA
Splittic-5.0.dist-info/WHEEL
Splittic-5.0.dist-info/top_level.txt
Splittic-5.0.dist-info/RECORD
