Metadata-Version: 2.1
Name: Splittic
Version: 5.0
Summary: The Most Advanced AI Ever
Home-page: https://github.com/Dart2004/Splittic-AI
Author: Daniel Klimmer
Author-email: danielklimmer2000@protonmail.com
License: MIT
Requires-Dist: requests
Requires-Dist: bs4
